{
  "data": [
    {
      "id": "bitcoin",
      "rank": "1",
      "symbol": "BTC",
      "name": "Bitcoin",
      "supply": "18859943.0000000000000000",
      "maxSupply": "21000000.0000000000000000",
      "marketCapUsd": "1143085021117.7609228604248984",
      "volumeUsd24Hr": "19072405659.1801018324797556",
      "priceUsd": "60609.1450603939218088",
      "changePercent24Hr": "-1.4022653136332386",
      "vwap24Hr": "61306.1680433456324563",
      "explorer": "https://blockchain.info/",
      "history": [
        {
          "priceUsd": "13765.7171904082127491",
          "time": 1604188800000,
          "date": "2020-11-01T00:00:00.000Z"
        },
        {
          "priceUsd": "13595.3549267387022142",
          "time": 1604275200000,
          "date": "2020-11-02T00:00:00.000Z"
        },
        {
          "priceUsd": "13612.2503100531120715",
          "time": 1604361600000,
          "date": "2020-11-03T00:00:00.000Z"
        },
        {
          "priceUsd": "13898.6385611360500221",
          "time": 1604448000000,
          "date": "2020-11-04T00:00:00.000Z"
        },
        {
          "priceUsd": "14720.6676075272725740",
          "time": 1604534400000,
          "date": "2020-11-05T00:00:00.000Z"
        }
      ]
    },
    {
      "id": "ethereum",
      "rank": "2",
      "symbol": "ETH",
      "name": "Ethereum",
      "supply": "118153082.1240000000000000",
      "maxSupply": null,
      "marketCapUsd": "500134012315.8456696221642043",
      "volumeUsd24Hr": "9465707405.3122993766701246",
      "priceUsd": "4232.9324239799521188",
      "changePercent24Hr": "-1.6401050436901671",
      "vwap24Hr": "4283.6456702348881211",
      "explorer": "https://etherscan.io/",
      "history": [
        {
          "priceUsd": "13765.7171904082127491",
          "time": 1604188800000,
          "date": "2020-11-01T00:00:00.000Z"
        },
        {
          "priceUsd": "13595.3549267387022142",
          "time": 1604275200000,
          "date": "2020-11-02T00:00:00.000Z"
        },
        {
          "priceUsd": "13612.2503100531120715",
          "time": 1604361600000,
          "date": "2020-11-03T00:00:00.000Z"
        },
        {
          "priceUsd": "13898.6385611360500221",
          "time": 1604448000000,
          "date": "2020-11-04T00:00:00.000Z"
        },
        {
          "priceUsd": "14720.6676075272725740",
          "time": 1604534400000,
          "date": "2020-11-05T00:00:00.000Z"
        }
      ]
    }
  ],
  "timestamp": 1635704883653
}
